ifree/__init__.py
ifree/dicom.py
ifree/main.py
ifree/processing.py
ifree/show.py
ifree/survival.py
ifree-1.1.1.dist-info/LICENSE
ifree-1.1.1.dist-info/METADATA
ifree-1.1.1.dist-info/WHEEL
ifree-1.1.1.dist-info/top_level.txt
ifree-1.1.1.dist-info/RECORD
