Metadata-Version: 2.1
Name: ifree
Version: 1.1.1
Summary: i love freedom, free my hand.
Home-page: https://github.com/linzhenyuyuchen/ifree
Author: Lin Zhenyu
Author-email: linzhenyu1996@gmail.com
License: BSD license
Keywords: ifree
Platform: UNKNOWN
Classifier: Development Status :: 2 - Pre-Alpha
Classifier: Intended Audience :: Developers
Classifier: License :: OSI Approved :: BSD License
Classifier: Natural Language :: English
Classifier: Programming Language :: Python :: 3.7
Classifier: Programming Language :: Python :: 3.6
Requires-Python: >=3.6
Requires-Dist: dicom2nifti
Requires-Dist: dicompyler-core
Requires-Dist: lifelines
Requires-Dist: itk
Requires-Dist: minepy
Requires-Dist: numpy
Requires-Dist: numpy (>=1.15.4)
Requires-Dist: pandas (>=0.24.2)
Requires-Dist: pyradiomics
Requires-Dist: scikit-image (>=0.14)
Requires-Dist: scipy
Requires-Dist: SimpleITK
Requires-Dist: sklearn
Requires-Dist: tqdm
Requires-Dist: vtk
